{
    "type": "betterendforge:infusion",
    "input": {
        "item": "mowziesmobs:wrought_helmet"
    },
    "output": {
        "id": "minecraft:diamond_helmet",
        "Count": 1,
        "tag": {
            "display": {
                "Name": "{\"translate\": \"item.soaring_depths.helmet\",\"color\": \"light_purple\",\"bold\": true,\"italic\": false}"
            },
            "RepairCost": 20,
            "AttributeModifiers": [
                {
                    "AttributeName": "generic.max_health",
                    "Name": "generic.max_health",
                    "Amount": 1,
                    "Operation": 0,
                    "UUID": [
                        406908201,698699477,-1315920193,1024514078
                    ],
                    "Slot": "head"
                },
                {
                    "AttributeName":"generic.luck",
                    "Name":"generic.luck",
                    "Amount":1,
                    "Operation":0,
                    "UUID":[
                        846493083,-1326429731,-1723277641,-1733768700
                    ],
                    "Slot":"head"
                },
                {
                    "AttributeName": "generic.armor",
                    "Name": "generic.armor",
                    "Amount": 3,
                    "Operation": 0,
                    "UUID": [
                        1971215365,-1098363312,-1695515322,-417499965
                    ],
                    "Slot": "head"
                },
                {
                    "AttributeName": "generic.armor_toughness",
                    "Name": "generic.armor_toughness",
                    "Amount": 2.5,
                    "Operation": 0,
                    "UUID": [
                        252407515,-1866905082,-1663024550,-1621122407
                    ],
                    "Slot": "head"
                }
            ]
        }
    },
    "time": 300,
    "catalysts": [
        {
            "item": {
                "item": "rubber_duck:rubber_duck_item"
            },
            "index": 0
        },
        {
            "item": {
                "item": "createaddition:diamond_grit"
            },
            "index": 1
        },
        {
            "item": {
                "item": "queen_bee:bee_antenna_helmet"
            },
            "index": 2
        },
        {
            "item": {
                "item": "createaddition:diamond_grit"
            },
            "index": 3
        },
        {
            "item": {
                "item": "forbidden_arcanus:eternal_stella"
            },
            "index": 4
        },
        {
            "item": {
                "item": "createaddition:diamond_grit"
            },
            "index": 5
        },
        {
            "item": {
                "item": "kobolds:kobold_block_skull"
            },
            "index": 6
        },
        {
            "item": {
                "item": "createaddition:diamond_grit"
            },
            "index": 7
        }
    ]
}